PyGraphLib/__init__.py
PyGraphLib/module.py
PyGraphLib/py.typed
PyGraphLib-0.0.7.dist-info/METADATA
PyGraphLib-0.0.7.dist-info/WHEEL
PyGraphLib-0.0.7.dist-info/top_level.txt
PyGraphLib-0.0.7.dist-info/RECORD
