Metadata-Version: 2.1
Name: PyGraphLib
Version: 0.0.7
Summary: A simple and incomplete graph library for Python
Project-URL: Homepage, https://github.com/HansLuft778/PyGraphLib
Requires-Python: >=3.7
Requires-Dist: matplotlib
